trove_query_parser/__init__.py
trove_query_parser/_nbdev.py
trove_query_parser/parser.py
trove_query_parser-0.2.1.dist-info/LICENSE
trove_query_parser-0.2.1.dist-info/METADATA
trove_query_parser-0.2.1.dist-info/WHEEL
trove_query_parser-0.2.1.dist-info/entry_points.txt
trove_query_parser-0.2.1.dist-info/top_level.txt
trove_query_parser-0.2.1.dist-info/RECORD
