Metadata-Version: 2.1
Name: trove-query-parser
Version: 0.2.1
Summary: Convert search parameters from the Trove web interface into a form the API understands.
Home-page: https://github.com/wragge/trove_query_parser/tree/master/
Author: Tim Sherratt
Author-email: tim@timsherratt.org
License: MIT License
Keywords: Trove
Platform: UNKNOWN
Classifier: Development Status :: 5 - Production/Stable
Classifier: Intended Audience :: Developers
Classifier: Natural Language :: English
Classifier: Programming Language :: Python :: 3.8
Classifier: License :: OSI Approved :: MIT License
Requires-Python: >=3.8
Requires-Dist: pip
Requires-Dist: packaging
Requires-Dist: requests
Requires-Dist: arrow
Provides-Extra: dev
